paradec/__init__.py
paradec/paradec.py
paradec-0.0.3.dist-info/LICENSE
paradec-0.0.3.dist-info/METADATA
paradec-0.0.3.dist-info/WHEEL
paradec-0.0.3.dist-info/top_level.txt
paradec-0.0.3.dist-info/RECORD
